LICENSE
MANIFEST.in
README.md
app.py
setup.cfg
setup.py
deepasr/__init__.py
deepasr.egg-info/PKG-INFO
deepasr.egg-info/SOURCES.txt
deepasr.egg-info/dependency_links.txt
deepasr.egg-info/requires.txt
deepasr.egg-info/top_level.txt
deepasr/augmentation/__init__.py
deepasr/augmentation/augmentation.py
deepasr/augmentation/spec_augment.py
deepasr/decoder/__init__.py
deepasr/decoder/decoder.py
deepasr/evaluate/__init__.py
deepasr/evaluate/activations.py
deepasr/evaluate/distance.py
deepasr/evaluate/evaluate.py
deepasr/features/__init__.py
deepasr/features/feature_extractor.py
deepasr/features/filter_banks.py
deepasr/features/get_features.py
deepasr/features/mfcc.py
deepasr/features/sigproc.py
deepasr/features/spectrogram.py
deepasr/model/__init__.py
deepasr/model/compilemodel.py
deepasr/model/deepasrnetwork1.py
deepasr/model/deepspeech2.py
deepasr/pipeline/__init__.py
deepasr/pipeline/ctc_pipeline.py
deepasr/pipeline/get_pipeline.py
deepasr/pipeline/pipeline.py
deepasr/utils/__init__.py
deepasr/utils/getmeta.py
deepasr/utils/utils.py
deepasr/vocab/__init__.py
deepasr/vocab/alphabet-en.txt
deepasr/vocab/alphabet.py