Metadata-Version: 2.1
Name: deepasr
Version: 0.1.2
Summary: Keras(Tensorflow) implementations of Automatic Speech Recognition
Home-page: https://github.com/scionoftech/DeepAsr
Author: Sai Kumar Yava
Author-email: saikumar.geek@gmail.com
License: GNU
Keywords: deepspeech,asr,speech recognition,speech to text
Platform: UNKNOWN
Requires-Python: >=3.6
